textcaptcha/__init__.py
textcaptcha/captcha.py
textcaptcha/captcha_fetcher.py
textcaptcha-0.2.0.dist-info/LICENSE
textcaptcha-0.2.0.dist-info/WHEEL
textcaptcha-0.2.0.dist-info/METADATA
textcaptcha-0.2.0.dist-info/RECORD
