Metadata-Version: 2.1
Name: textcaptcha
Version: 0.2.0
Summary: A library for using text-based CAPTCHAs from http://textcaptcha.com/.
Home-page: https://github.com/jake-walker/pytextcaptcha
License: GPL-3.0-only
Author: Jake Walker
Author-email: hi@jakew.me
Requires-Python: >=3.6,<4.0
Classifier: License :: OSI Approved :: GNU General Public License v3 (GPLv3)
Classifier: Programming Language :: Python :: 3
Classifier: Programming Language :: Python :: 3.6
Classifier: Programming Language :: Python :: 3.7
Requires-Dist: requests (>=2.22.0,<3.0.0)
Project-URL: Repository, https://github.com/jake-walker/pytextcaptcha.git
